[{"parser_files_categorization_values": "Windows PowerShell.evtx", "important_field": [{"path": "RecordID", "name": "RecordID"}, {"path": "Exeution", "name": "Exeution"}, {"path": "Base64", "name": "Base64"}], "name": "PowerShell-Analyzer", "interface_function": "PowerShell-Analyzer_interface.imain", "parser_files_categorization_type": "file_name", "creation_time": "2022-07-16T00:36:27.099717", "parser_type_field": "logging_information", "action": "add", "parser_folder": "PowerShell-Analyzer", "_id": "PowerShell-Analyzer", "description": "Remove False Positive, minimize the logs, decode Base64 if detected"}]
